pymodaq_gui/__init__.py
pymodaq_gui/config_saver_loader.py
pymodaq_gui/messenger.py
pymodaq_gui/qt_utils.py
pymodaq_gui/qvariant.py
pymodaq_gui/splash.png
pymodaq_gui/QtDesigner_Ressources/credit.rst
pymodaq_gui/QtDesigner_Ressources/icons.svg
pymodaq_gui/QtDesigner_Ressources/Icon_Library/1d.png
pymodaq_gui/QtDesigner_Ressources/Icon_Library/2d.png
pymodaq_gui/QtDesigner_Ressources/Icon_Library/3d.png
pymodaq_gui/QtDesigner_Ressources/Icon_Library/Add2.png
pymodaq_gui/QtDesigner_Ressources/Icon_Library/Add_Step.png
pymodaq_gui/QtDesigner_Ressources/Icon_Library/Approve.png
pymodaq_gui/QtDesigner_Ressources/Icon_Library/Approve_All.png
pymodaq_gui/QtDesigner_Ressources/Icon_Library/Browse_Dir_Path.png
pymodaq_gui/QtDesigner_Ressources/Icon_Library/Calculator.png
pymodaq_gui/QtDesigner_Ressources/Icon_Library/ChnGroup.png
pymodaq_gui/QtDesigner_Ressources/Icon_Library/ChnNum.png
pymodaq_gui/QtDesigner_Ressources/Icon_Library/ChnText.png
pymodaq_gui/QtDesigner_Ressources/Icon_Library/ChnTime.png
pymodaq_gui/QtDesigner_Ressources/Icon_Library/ChnWave.png
pymodaq_gui/QtDesigner_Ressources/Icon_Library/Close3.png
pymodaq_gui/QtDesigner_Ressources/Icon_Library/CollapseAll.png
pymodaq_gui/QtDesigner_Ressources/Icon_Library/CollapseAll_32.png
pymodaq_gui/QtDesigner_Ressources/Icon_Library/ColorPicker.png
pymodaq_gui/QtDesigner_Ressources/Icon_Library/Contract.png
pymodaq_gui/QtDesigner_Ressources/Icon_Library/Create.png
pymodaq_gui/QtDesigner_Ressources/Icon_Library/DeleteLayer.png
pymodaq_gui/QtDesigner_Ressources/Icon_Library/EditOpen.png
pymodaq_gui/QtDesigner_Ressources/Icon_Library/EditRedo.png
pymodaq_gui/QtDesigner_Ressources/Icon_Library/EditUndo.png
pymodaq_gui/QtDesigner_Ressources/Icon_Library/Ellipse.png
pymodaq_gui/QtDesigner_Ressources/Icon_Library/EllipseFilled.png
pymodaq_gui/QtDesigner_Ressources/Icon_Library/Error.png
pymodaq_gui/QtDesigner_Ressources/Icon_Library/ErrorMessage.png
pymodaq_gui/QtDesigner_Ressources/Icon_Library/Error_16.png
pymodaq_gui-5.1.7.dist-info/METADATA
pymodaq_gui-5.1.7.dist-info/WHEEL
pymodaq_gui-5.1.7.dist-info/entry_points.txt
pymodaq_gui-5.1.7.dist-info/licenses/LICENSE
pymodaq_gui-5.1.7.dist-info/RECORD
