Metadata-Version: 2.4
Name: pymodaq_gui
Version: 5.1.7
Summary: User Interface components for PyMoDAQ
Project-URL: Homepage, http://pymodaq.cnrs.fr
Project-URL: Source, https://github.com/PyMoDAQ/PyMoDAQ
Project-URL: Tracker, https://github.com/PyMoDAQ/PyMoDAQ/issues
Author-email: Sébastien Weber <sebastien.weber@cemes.fr>
License: The MIT License (MIT)
License-File: LICENSE
Classifier: Development Status :: 5 - Production/Stable
Classifier: Environment :: Other Environment
Classifier: Intended Audience :: Science/Research
Classifier: License :: OSI Approved :: MIT License
Classifier: Natural Language :: English
Classifier: Operating System :: OS Independent
Classifier: Programming Language :: Python :: 3.9
Classifier: Programming Language :: Python :: 3.10
Classifier: Programming Language :: Python :: 3.11
Classifier: Programming Language :: Python :: 3.12
Classifier: Topic :: Scientific/Engineering :: Human Machine Interfaces
Classifier: Topic :: Scientific/Engineering :: Visualization
Classifier: Topic :: Software Development :: Libraries :: Python Modules
Classifier: Topic :: Software Development :: User Interfaces
Requires-Python: >=3.8
Requires-Dist: easydict
Requires-Dist: pymodaq-data>=5.0.13
Requires-Dist: pymodaq-utils>=0.0.8
Requires-Dist: pyqtgraph<0.14,>=0.12
Requires-Dist: qtpy
Provides-Extra: dev
Requires-Dist: flake8; extra == 'dev'
Requires-Dist: hatch; extra == 'dev'
Requires-Dist: pyqt5; extra == 'dev'
Requires-Dist: pyqt6; extra == 'dev'
Requires-Dist: pyside6; extra == 'dev'
Requires-Dist: pytest; extra == 'dev'
Requires-Dist: pytest-cov; extra == 'dev'
Requires-Dist: pytest-qt; extra == 'dev'
Requires-Dist: pytest-xdist; extra == 'dev'
Requires-Dist: pytest-xvfb; extra == 'dev'
